claude/__init__.py
claude/claude_client.py
claude/claude_wrapper.py
claude/constants.py
claude/custom_requests.py
claude/custom_types.py
claude/helpers.py
claude/logger.py
claude_api_py-0.0.5.dist-info/LICENSE
claude_api_py-0.0.5.dist-info/METADATA
claude_api_py-0.0.5.dist-info/WHEEL
claude_api_py-0.0.5.dist-info/top_level.txt
claude_api_py-0.0.5.dist-info/RECORD
