Metadata-Version: 2.1
Name: claude-api-py
Version: 0.0.5
Summary: Unofficial Anthropic Claude API for Python3.
Home-page: https://github.com/AshwinPathi/claude-api-py
License: MIT
Keywords: llm,claude,api,gpt
Classifier: Development Status :: 3 - Alpha
Classifier: Intended Audience :: Developers
Classifier: Topic :: Software Development :: Build Tools
Classifier: License :: OSI Approved :: MIT License
Classifier: Programming Language :: Python :: 3.4
Classifier: Programming Language :: Python :: 3.5
Classifier: Programming Language :: Python :: 3.6
Classifier: Programming Language :: Python :: 3.7
Classifier: Programming Language :: Python :: 3.8
Classifier: Programming Language :: Python :: 3.9
License-File: LICENSE
Requires-Dist: sseclient-py
